correctionlib_gradients/__about__.py
correctionlib_gradients/__init__.py
correctionlib_gradients/_compound_binning.py
correctionlib_gradients/_correction_with_gradient.py
correctionlib_gradients/_correctiondag.py
correctionlib_gradients/_formuladag.py
correctionlib_gradients/_spline_with_grad.py
correctionlib_gradients/_typedefs.py
correctionlib_gradients/_utils.py
correctionlib_gradients/py.typed
correctionlib_gradients-0.2.2.dist-info/METADATA
correctionlib_gradients-0.2.2.dist-info/WHEEL
correctionlib_gradients-0.2.2.dist-info/licenses/LICENSE.txt
correctionlib_gradients-0.2.2.dist-info/RECORD
