Metadata-Version: 2.1
Name: correctionlib-gradients
Version: 0.2.2
Summary: Automatic differentiation for high-energy physics correction factor calculations.
Project-URL: Documentation, https://github.com/eguiraud/correctionlib-gradients#readme
Project-URL: Issues, https://github.com/eguiraud/correctionlib-gradients/issues
Project-URL: Source, https://github.com/eguiraud/correctionlib-gradients
Author-email: Enrico Guiraud <enrico.guiraud@pm.me>
License: BSD-3-Clause
License-File: LICENSE.txt
Classifier: Development Status :: 4 - Beta
Classifier: Intended Audience :: Science/Research
Classifier: Programming Language :: Python
Classifier: Programming Language :: Python :: 3.10
Classifier: Programming Language :: Python :: 3.11
Classifier: Programming Language :: Python :: Implementation :: CPython
Classifier: Programming Language :: Python :: Implementation :: PyPy
Classifier: Topic :: Scientific/Engineering :: Physics
Requires-Python: >=3.10
Requires-Dist: correctionlib>=2.4.0
Requires-Dist: jax
Requires-Dist: jaxlib
Requires-Dist: scipy
